{
	"info": {
		"_postman_id": "395d17a8-4a58-49a5-82a8-254950eee697",
		"name": "Login",
		"schema": "https://schema.getpostman.com/json/collection/v2.1.0/collection.json",
		"_exporter_id": "12081671"
	},
	"item": [
		{
			"name": "Login",
			"event": [
				{
					"listen": "test",
					"script": {
						"exec": [
							"pm.test(\"Status code is 200\", function () {\r",
							"    pm.response.to.have.status(200);\r",
							"});\r",
							"var jsonData = JSON.parse(responseBody);\r",
							"postman.setEnvironmentVariable(\"AdminToken\", jsonData.api_token);\r",
							""
						],
						"type": "text/javascript"
					}
				}
			],
			"request": {
				"method": "POST",
				"header": [],
				"body": {
					"mode": "formdata",
					"formdata": [
						{
							"key": "email",
							"value": "admin@admin.com",
							"type": "text"
						},
						{
							"key": "password",
							"value": "adminpass",
							"type": "text"
						}
					]
				},
				"url": {
					"raw": "http://127.0.0.1:8000/api/login",
					"protocol": "http",
					"host": [
						"127",
						"0",
						"0",
						"1"
					],
					"port": "8000",
					"path": [
						"api",
						"login"
					]
				}
			},
			"response": []
		},
		{
			"name": "Get all pengajar Copy",
			"event": [
				{
					"listen": "test",
					"script": {
						"exec": [
							"pm.test(\"Status code is 200\", function () {\r",
							"    pm.response.to.have.status(200);\r",
							"});\r",
							"const jsonData = JSON.parse(responseBody);\r",
							"let keys = Object.keys(jsonData);   \r",
							"const index = Math.trunc(Math.random() * 40);\r",
							"const item = keys[index];\r",
							"pm.environment.set(\"pengajar_email\", jsonData[item].email);\r",
							"\r",
							""
						],
						"type": "text/javascript"
					}
				}
			],
			"request": {
				"auth": {
					"type": "bearer",
					"bearer": [
						{
							"key": "token",
							"value": "{{AdminToken}}",
							"type": "string"
						}
					]
				},
				"method": "GET",
				"header": [],
				"url": {
					"raw": "http://127.0.0.1:8000/api/user/pengajar",
					"protocol": "http",
					"host": [
						"127",
						"0",
						"0",
						"1"
					],
					"port": "8000",
					"path": [
						"api",
						"user",
						"pengajar"
					]
				}
			},
			"response": []
		},
		{
			"name": "Get all siswa Copy",
			"event": [
				{
					"listen": "test",
					"script": {
						"exec": [
							"pm.test(\"Status code is 200\", function () {\r",
							"    pm.response.to.have.status(200);\r",
							"});\r",
							"const jsonData = JSON.parse(responseBody);\r",
							"let keys = Object.keys(jsonData);   \r",
							"const index = Math.trunc(Math.random() * 80);\r",
							"const item = keys[index];\r",
							"\r",
							"pm.environment.set(\"siswa_email\", jsonData[item].email);"
						],
						"type": "text/javascript"
					}
				}
			],
			"request": {
				"auth": {
					"type": "bearer",
					"bearer": [
						{
							"key": "token",
							"value": "{{AdminToken}}",
							"type": "string"
						}
					]
				},
				"method": "GET",
				"header": [],
				"url": {
					"raw": "http://127.0.0.1:8000/api/user/siswa",
					"protocol": "http",
					"host": [
						"127",
						"0",
						"0",
						"1"
					],
					"port": "8000",
					"path": [
						"api",
						"user",
						"siswa"
					]
				}
			},
			"response": []
		},
		{
			"name": "Login siswa",
			"event": [
				{
					"listen": "test",
					"script": {
						"exec": [
							"pm.test(\"Status code is 200\", function () {\r",
							"    pm.response.to.have.status(200);\r",
							"});\r",
							"var jsonData = JSON.parse(responseBody);\r",
							"postman.setEnvironmentVariable(\"SiswaToken\", jsonData.api_token);"
						],
						"type": "text/javascript"
					}
				}
			],
			"request": {
				"method": "POST",
				"header": [],
				"body": {
					"mode": "formdata",
					"formdata": [
						{
							"key": "email",
							"value": "{{siswa_email}}",
							"type": "text"
						},
						{
							"key": "password",
							"value": "test",
							"type": "text"
						}
					]
				},
				"url": {
					"raw": "http://127.0.0.1:8000/api/login",
					"protocol": "http",
					"host": [
						"127",
						"0",
						"0",
						"1"
					],
					"port": "8000",
					"path": [
						"api",
						"login"
					]
				}
			},
			"response": []
		},
		{
			"name": "Login pengajar",
			"event": [
				{
					"listen": "test",
					"script": {
						"exec": [
							"pm.test(\"Status code is 200\", function () {\r",
							"    pm.response.to.have.status(200);\r",
							"});\r",
							"var jsonData = JSON.parse(responseBody);\r",
							"postman.setEnvironmentVariable(\"PengajarToken\", jsonData.api_token);"
						],
						"type": "text/javascript"
					}
				}
			],
			"request": {
				"method": "POST",
				"header": [],
				"body": {
					"mode": "formdata",
					"formdata": [
						{
							"key": "email",
							"value": "{{pengajar_email}}",
							"type": "text"
						},
						{
							"key": "password",
							"value": "test",
							"type": "text"
						}
					]
				},
				"url": {
					"raw": "http://127.0.0.1:8000/api/login",
					"protocol": "http",
					"host": [
						"127",
						"0",
						"0",
						"1"
					],
					"port": "8000",
					"path": [
						"api",
						"login"
					]
				}
			},
			"response": []
		}
	],
	"variable": [
		{
			"key": "pengajar_email",
			"value": ""
		},
		{
			"key": "siswa_email",
			"value": ""
		}
	]
}